notify/__init__.py
notify/__main__.py
notify/_version.py
notify/conf.py
notify/exceptions.c
notify/exceptions.cpython-310-x86_64-linux-gnu.so
notify/exceptions.pxd
notify/exceptions.pyx
notify/models.py
notify/notify.py
notify/py.typed
notify/templates.py
notify/version.py
notify/providers/__init__.py
notify/providers/base.py
notify/providers/mail.py
notify/providers/message.py
notify/providers/aws/__init__.py
notify/providers/aws/aws.py
notify/providers/dialpad/__init__.py
notify/providers/dialpad/dialpad.py
notify/providers/dummy/__init__.py
notify/providers/dummy/dummy.py
notify/providers/email/__init__.py
notify/providers/email/email.py
notify/providers/gmail/__init__.py
notify/providers/gmail/gmail.py
notify/providers/office365/__init__.py
notify/providers/office365/office365.py
notify/providers/onesignal/__init__.py
notify/providers/onesignal/onesignal.py
notify/providers/outlook/__init__.py
notify/providers/outlook/outlook.py
notify/providers/sendgrid/__init__.py
notify/providers/sendgrid/sendgrid.py
notify/providers/ses/__init__.py
notify/providers/ses/ses.py
notify/providers/slack/__init__.py
notify/providers/slack/slack.py
notify/providers/smtp/__init__.py
notify/providers/smtp/smtp.py
notify/providers/teams/__init__.py
notify/providers/teams/teams.py
notify/providers/telegram/Telegram.py
notify/providers/telegram/__init__.py
notify/providers/twilio/__init__.py
notify/providers/twilio/twilio.py
notify/providers/xmpp/__init__.py
notify/providers/xmpp/xmpp.py
notify/server/__init__.py
notify/server/client.py
notify/server/py.typed
notify/server/queue.py
notify/server/server.py
notify/server/wrapper.py
notify/tests/__init__.py
notify/tests/base.py
notify/types/__init__.py
notify/types/typedefs.c
notify/types/typedefs.cpython-310-x86_64-linux-gnu.so
notify/types/typedefs.pyx
notify/utils/__init__.py
notify/utils/functions.py
async_notify-1.5.3.dist-info/METADATA
async_notify-1.5.3.dist-info/WHEEL
async_notify-1.5.3.dist-info/entry_points.txt
async_notify-1.5.3.dist-info/top_level.txt
async_notify-1.5.3.dist-info/RECORD
async_notify-1.5.3.dist-info/licenses/LICENSE
